feed_seeker/__init__.py
feed_seeker/feed_seeker.py
feed_seeker-1.0.0.dist-info/DESCRIPTION.rst
feed_seeker-1.0.0.dist-info/METADATA
feed_seeker-1.0.0.dist-info/RECORD
feed_seeker-1.0.0.dist-info/WHEEL
feed_seeker-1.0.0.dist-info/metadata.json
feed_seeker-1.0.0.dist-info/top_level.txt
