Metadata-Version: 2.0
Name: feed-seeker
Version: 1.0.0
Summary: Extract rss, atom, and other feeds from webpages
Home-page: https://github.com/mitmedialab/feed_seeker
Author: Colin Carroll
Author-email: ccarroll@mit.edu
License: MIT
Platform: UNKNOWN
Classifier: Development Status :: 3 - Alpha
Classifier: Intended Audience :: Developers
Classifier: License :: OSI Approved :: MIT License
Classifier: Programming Language :: Python :: 3
Classifier: Programming Language :: Python :: 3.6
Requires-Dist: beautifulsoup4 (>=4.6.0)
Requires-Dist: lxml (>=4.1.1)
Requires-Dist: requests (>=2.18.4)
